README.rst
setup.py
new_demo/__init__.py
new_demo/__main__.py
new_demo/new_demo.py
new_demo.egg-info/PKG-INFO
new_demo.egg-info/SOURCES.txt
new_demo.egg-info/dependency_links.txt
new_demo.egg-info/entry_points.txt
new_demo.egg-info/top_level.txt