Metadata-Version: 1.0
Name: new-demo
Version: 0.1.1
Summary: Python command line html creator
Home-page: https://github.com/oscarvazquez/command_line_tool_demo
Author: Justin Niu
Author-email: jusman@gmail.com
License: UNKNOWN
Platform: UNKNOWN
